{
    "moves": [
        {
            "Level": "1",
            "Move": "Growl",
            "Type": "Normal",
            "Pwr": "--",
            "Acc": "100%",
            "PP": "40",
            "LearnType": "LevelingUp"
        },
        {
            "Level": "4",
            "Move": "Thunder Wave",
            "Type": "Electric",
            "Pwr": "--",
            "Acc": "100%",
            "PP": "20",
            "LearnType": "LevelingUp"
        },
        {
            "Level": "10",
            "Move": "Quick Attack",
            "Type": "Normal",
            "Pwr": "40",
            "Acc": "100%",
            "PP": "30",
            "LearnType": "LevelingUp"
        },
        {
            "Level": "13",
            "Move": "Helping Hand",
            "Type": "Normal",
            "Pwr": "--",
            "Acc": "--%",
            "PP": "20",
            "LearnType": "LevelingUp"
        },
        {
            "Level": "19",
            "Move": "Spark",
            "Type": "Electric",
            "Pwr": "65",
            "Acc": "100%",
            "PP": "20",
            "LearnType": "LevelingUp"
        },
        {
            "Level": "22",
            "Move": "Encore",
            "Type": "Normal",
            "Pwr": "--",
            "Acc": "100%",
            "PP": "5",
            "LearnType": "LevelingUp"
        },
        {
            "Level": "28",
            "Move": "Charm",
            "Type": "Normal",
            "Pwr": "--",
            "Acc": "100%",
            "PP": "20",
            "LearnType": "LevelingUp"
        },
        {
            "Level": "31",
            "Move": "Charge",
            "Type": "Electric",
            "Pwr": "--",
            "Acc": "--%",
            "PP": "20",
            "LearnType": "LevelingUp"
        },
        {
            "Level": "37",
            "Move": "Thunder",
            "Type": "Electric",
            "Pwr": "120",
            "Acc": "70%",
            "PP": "10",
            "LearnType": "LevelingUp"
        },
        {
            "Level": "40",
            "Move": "Baton Pass",
            "Type": "Normal",
            "Pwr": "--",
            "Acc": "--%",
            "PP": "40",
            "LearnType": "LevelingUp"
        },
        {
            "Level": "47",
            "Move": "Agility",
            "Type": "Psychic",
            "Pwr": "--",
            "Acc": "--%",
            "PP": "30",
            "LearnType": "LevelingUp"
        },
        {
            "TM": "",
            "Move": "TM06",
            "Type": "Toxic",
            "Pwr": "Poison",
            "Acc": "--",
            "PP": "85%",
            "LearnType": "Tm.2Fhm"
        },
        {
            "TM": "",
            "Move": "TM10",
            "Type": "Hidden Power",
            "Pwr": "Normal",
            "Acc": "--",
            "PP": "100%",
            "LearnType": "Tm.2Fhm"
        },
        {
            "TM": "",
            "Move": "TM16",
            "Type": "Light Screen",
            "Pwr": "Psychic",
            "Acc": "--",
            "PP": "--%",
            "LearnType": "Tm.2Fhm"
        },
        {
            "TM": "",
            "Move": "TM17",
            "Type": "Protect",
            "Pwr": "Normal",
            "Acc": "--",
            "PP": "--%",
            "LearnType": "Tm.2Fhm"
        },
        {
            "TM": "",
            "Move": "TM18",
            "Type": "Rain Dance",
            "Pwr": "Water",
            "Acc": "--",
            "PP": "--%",
            "LearnType": "Tm.2Fhm"
        },
        {
            "TM": "",
            "Move": "TM21",
            "Type": "Frustration",
            "Pwr": "Normal",
            "Acc": "--",
            "PP": "100%",
            "LearnType": "Tm.2Fhm"
        },
        {
            "TM": "",
            "Move": "TM23",
            "Type": "Iron Tail",
            "Pwr": "Steel",
            "Acc": "100",
            "PP": "75%",
            "LearnType": "Tm.2Fhm"
        },
        {
            "TM": "",
            "Move": "TM24",
            "Type": "Thunderbolt",
            "Pwr": "Electric",
            "Acc": "95",
            "PP": "100%",
            "LearnType": "Tm.2Fhm"
        },
        {
            "TM": "",
            "Move": "TM25",
            "Type": "Thunder",
            "Pwr": "Electric",
            "Acc": "120",
            "PP": "70%",
            "LearnType": "Tm.2Fhm"
        },
        {
            "TM": "",
            "Move": "TM27",
            "Type": "Return",
            "Pwr": "Normal",
            "Acc": "--",
            "PP": "100%",
            "LearnType": "Tm.2Fhm"
        },
        {
            "TM": "",
            "Move": "TM32",
            "Type": "Double Team",
            "Pwr": "Normal",
            "Acc": "--",
            "PP": "--%",
            "LearnType": "Tm.2Fhm"
        },
        {
            "TM": "",
            "Move": "TM34",
            "Type": "Shock Wave",
            "Pwr": "Electric",
            "Acc": "60",
            "PP": "--%",
            "LearnType": "Tm.2Fhm"
        },
        {
            "TM": "",
            "Move": "TM42",
            "Type": "Facade",
            "Pwr": "Normal",
            "Acc": "70",
            "PP": "100%",
            "LearnType": "Tm.2Fhm"
        },
        {
            "TM": "",
            "Move": "TM43",
            "Type": "Secret Power",
            "Pwr": "Normal",
            "Acc": "70",
            "PP": "100%",
            "LearnType": "Tm.2Fhm"
        },
        {
            "TM": "",
            "Move": "TM44",
            "Type": "Rest",
            "Pwr": "Psychic",
            "Acc": "--",
            "PP": "--%",
            "LearnType": "Tm.2Fhm"
        },
        {
            "TM": "",
            "Move": "TM45",
            "Type": "Attract",
            "Pwr": "Normal",
            "Acc": "--",
            "PP": "100%",
            "LearnType": "Tm.2Fhm"
        },
        {
            "TM": "",
            "Move": "HM05",
            "Type": "Flash",
            "Pwr": "Normal",
            "Acc": "--",
            "PP": "70%",
            "LearnType": "Tm.2Fhm"
        },
        {
            "Father": "",
            "Move": "Substitute",
            "Type": "Normal",
            "Pwr": "--",
            "Acc": "--%",
            "PP": "10",
            "LearnType": "Breeding"
        },
        {
            "Father": "",
            "Move": "Wish",
            "Type": "Normal",
            "Pwr": "--",
            "Acc": "--%",
            "PP": "10",
            "LearnType": "Breeding"
        },
        {
            "Game": "FRLGEXD",
            "Move": "Body Slam",
            "Type": "Normal",
            "Pwr": "85",
            "Acc": "100%",
            "PP": "15",
            "LearnType": "Tutoring"
        },
        {
            "Game": "FRLGE",
            "Move": "Counter",
            "Type": "Fighting",
            "Pwr": "--",
            "Acc": "100%",
            "PP": "20",
            "LearnType": "Tutoring"
        },
        {
            "Game": "E",
            "Move": "Defense Curl",
            "Type": "Normal",
            "Pwr": "--",
            "Acc": "--%",
            "PP": "40",
            "LearnType": "Tutoring"
        },
        {
            "Game": "FRLGEXD",
            "Move": "Double-Edge",
            "Type": "Normal",
            "Pwr": "120",
            "Acc": "100%",
            "PP": "15",
            "LearnType": "Tutoring"
        },
        {
            "Game": "E",
            "Move": "DynamicPunch",
            "Type": "Fighting",
            "Pwr": "100",
            "Acc": "50%",
            "PP": "5",
            "LearnType": "Tutoring"
        },
        {
            "Game": "E",
            "Move": "Endure",
            "Type": "Normal",
            "Pwr": "--",
            "Acc": "--%",
            "PP": "10",
            "LearnType": "Tutoring"
        },
        {
            "Game": "FRLGE",
            "Move": "Mega Kick",
            "Type": "Normal",
            "Pwr": "120",
            "Acc": "75%",
            "PP": "5",
            "LearnType": "Tutoring"
        },
        {
            "Game": "FRLGE",
            "Move": "Mega Punch",
            "Type": "Normal",
            "Pwr": "80",
            "Acc": "85%",
            "PP": "20",
            "LearnType": "Tutoring"
        },
        {
            "Game": "FRLGE",
            "Move": "Metronome",
            "Type": "Normal",
            "Pwr": "--",
            "Acc": "--%",
            "PP": "10",
            "LearnType": "Tutoring"
        },
        {
            "Game": "FRLGEXD",
            "Move": "Mimic",
            "Type": "Normal",
            "Pwr": "--",
            "Acc": "--%",
            "PP": "10",
            "LearnType": "Tutoring"
        },
        {
            "Game": "E",
            "Move": "Mud-Slap",
            "Type": "Ground",
            "Pwr": "20",
            "Acc": "100%",
            "PP": "10",
            "LearnType": "Tutoring"
        },
        {
            "Game": "E",
            "Move": "Rollout",
            "Type": "Rock",
            "Pwr": "30",
            "Acc": "90%",
            "PP": "20",
            "LearnType": "Tutoring"
        },
        {
            "Game": "FRLGEXD",
            "Move": "Seismic Toss",
            "Type": "Fighting",
            "Pwr": "--",
            "Acc": "100%",
            "PP": "20",
            "LearnType": "Tutoring"
        },
        {
            "Game": "E",
            "Move": "Sleep Talk",
            "Type": "Normal",
            "Pwr": "--",
            "Acc": "--%",
            "PP": "10",
            "LearnType": "Tutoring"
        },
        {
            "Game": "E",
            "Move": "Snore",
            "Type": "Normal",
            "Pwr": "40",
            "Acc": "100%",
            "PP": "15",
            "LearnType": "Tutoring"
        },
        {
            "Game": "FRLGEXD",
            "Move": "Substitute",
            "Type": "Normal",
            "Pwr": "--",
            "Acc": "--%",
            "PP": "10",
            "LearnType": "Tutoring"
        },
        {
            "Game": "EXD",
            "Move": "Swagger",
            "Type": "Normal",
            "Pwr": "--",
            "Acc": "90%",
            "PP": "15",
            "LearnType": "Tutoring"
        },
        {
            "Game": "E",
            "Move": "Swift",
            "Type": "Normal",
            "Pwr": "60",
            "Acc": "--%",
            "PP": "20",
            "LearnType": "Tutoring"
        },
        {
            "Game": "E",
            "Move": "ThunderPunch",
            "Type": "Electric",
            "Pwr": "75",
            "Acc": "100%",
            "PP": "15",
            "LearnType": "Tutoring"
        },
        {
            "Game": "FRLGEXD",
            "Move": "Thunder Wave",
            "Type": "Electric",
            "Pwr": "--",
            "Acc": "100%",
            "PP": "20",
            "LearnType": "Tutoring"
        }
    ],
    "stats": {
        "HP": "60",
        "Attack": "40",
        "Defense": "50",
        "Sp. Atk": "75",
        "Sp. Def": "85",
        "Speed": "95"
    },
    "dex_number": 81
}